fastapi_helmet/__init__.py
fastapi_helmet/core.py
fastapi_helmet/middleware.py
fastapi_helmet/settings.py
fastapi_helmet/utils.py
fastapi_helmet-0.1.0.dist-info/LICENSE
fastapi_helmet-0.1.0.dist-info/METADATA
fastapi_helmet-0.1.0.dist-info/WHEEL
fastapi_helmet-0.1.0.dist-info/RECORD
