Metadata-Version: 2.1
Name: fastapi-helmet
Version: 0.1.0
Summary: 
Author: Akhileshthykkat
Author-email: akhileshthykkat843@gmail.com
Requires-Python: >=3.10,<4.0
Classifier: Programming Language :: Python :: 3
Classifier: Programming Language :: Python :: 3.10
Classifier: Programming Language :: Python :: 3.11
Classifier: Programming Language :: Python :: 3.12
Requires-Dist: fastapi (>=0.111.0,<0.112.0)
Requires-Dist: pydantic (>=2.7.2,<3.0.0)
Requires-Dist: setuptools (>=70.0.0,<71.0.0)
Requires-Dist: twine (>=5.1.0,<6.0.0)
Requires-Dist: wheel (>=0.43.0,<0.44.0)
